sweep3d-0.1.0.dist-info/RECORD
sweep3d-0.1.0.dist-info/WHEEL
sweep3d-0.1.0.dist-info/METADATA
sweep3d-0.1.0.dist-info/licenses/LICENSE.txt
sweep3d/pysweep3d.cpython-310-darwin.so
sweep3d/__init__.py
sweep3d/libnanothread.dylib
sweep3d/__main__.py
