Metadata-Version: 2.2
Name: sweep3d
Version: 0.1.0
Summary: Implementation of 'Lifted Surfacing of Generalized Sweep Volumes'
Maintainer-Email: Qingnan Zhou <qnzhou@gmail.com>
Requires-Python: >=3.10
Requires-Dist: lagrange-open>=6.39
